gbdtCBL/__init__.py
gbdtCBL/binary.py
gbdtCBL/binarycupy.py
gbdtCBL/lgbmulti.py
gbdtCBL/multicupy.py
gbdtCBL/xgbmulti.py
gbdtCBL-0.1.dist-info/LICENSE
gbdtCBL-0.1.dist-info/METADATA
gbdtCBL-0.1.dist-info/WHEEL
gbdtCBL-0.1.dist-info/top_level.txt
gbdtCBL-0.1.dist-info/RECORD
