Metadata-Version: 2.1
Name: gbdtCBL
Version: 0.1
Summary: A package containing class-balanced loss functions for gradient boosting decision tree
Home-page: https://github.com/Luojiaqimath/ClassbalancedLoss4GBDT
Author: Jiaqi Luo, Yuan Yuan, Shixin Xu
Author-email: jiaqi.luo.jqluo@outlook.com
Classifier: Programming Language :: Python :: 3
Classifier: License :: OSI Approved :: MIT License
Classifier: Operating System :: OS Independent
Requires-Python: >=3.9,<3.12
License-File: LICENSE
Requires-Dist: numpy
Requires-Dist: scikit-learn
